k2/__init__.py
k2/csrc/README.md
k2/csrc/algorithms.h
k2/csrc/array.h
k2/csrc/array_inl.h
k2/csrc/array_ops.h
k2/csrc/array_ops_inl.h
k2/csrc/context.h
k2/csrc/dtype.h
k2/csrc/eval.h
k2/csrc/fsa.h
k2/csrc/fsa_algo.h
k2/csrc/fsa_utils.h
k2/csrc/host/arcsort.h
k2/csrc/host/array.h
k2/csrc/host/aux_labels.h
k2/csrc/host/connect.h
k2/csrc/host/dense_fsa.h
k2/csrc/host/determinize.h
k2/csrc/host/determinize_impl.h
k2/csrc/host/fsa.h
k2/csrc/host/fsa_equivalent.h
k2/csrc/host/fsa_renderer.h
k2/csrc/host/fsa_util.h
k2/csrc/host/intersect.h
k2/csrc/host/properties.h
k2/csrc/host/rmepsilon.h
k2/csrc/host/topsort.h
k2/csrc/host/util.h
k2/csrc/host/weights.h
k2/csrc/host_shim.h
k2/csrc/log.h
k2/csrc/math.h
k2/csrc/moderngpu_allocator.h
k2/csrc/nvtx.h
k2/csrc/pytorch_context.h
k2/csrc/ragged.h
k2/csrc/ragged_ops.h
k2/csrc/ragged_ops_inl.h
k2/csrc/tensor.h
k2/csrc/tensor_ops.h
k2/csrc/test_utils.h
k2/csrc/timer.h
k2/csrc/utils.h
k2/csrc/utils_inl.h
k2/docs/Makefile
k2/docs/make.bat
k2/docs/source/_static/.gitkeep
k2/docs/source/_templates/.gitkeep
k2/docs/source/conf.py
k2/docs/source/index.rst
k2/docs/source/python_api/array.rst
k2/docs/source/python_api/fsa.rst
k2/docs/source/python_api/symbol_table.rst
k2/python/__init__.py
k2/python/csrc/k2.h
k2/python/csrc/torch/arc.h
k2/python/csrc/torch/fsa.h
k2/python/csrc/torch/fsa_algo.h
k2/python/csrc/torch/index_add.h
k2/python/csrc/torch/index_select.h
k2/python/csrc/torch/ragged.h
k2/python/csrc/torch/torch_util.h
k2/python/csrc/torch.h
k2/python/csrc/version.h
k2/python/k2/__init__.py
k2/python/k2/autograd.py
k2/python/k2/autograd_utils.py
k2/python/k2/dense_fsa_vec.py
k2/python/k2/fsa.py
k2/python/k2/fsa_algo.py
k2/python/k2/fsa_properties.py
k2/python/k2/ops.py
k2/python/k2/ragged/__init__.py
k2/python/k2/ragged/ops.py
k2/python/k2/symbol_table.py
k2/python/k2/utils.py
k2/python/k2/version.py
k2/CMakeLists.txt
k2/libtest_utils.so
k2/_k2.cpython-38-x86_64-linux-gnu.so
k2/libk2fsa.so
k2/_k2host.cpython-38-x86_64-linux-gnu.so
k2_nailuo-0.1.3.dist-info/LICENSE
k2_nailuo-0.1.3.dist-info/WHEEL
k2_nailuo-0.1.3.dist-info/METADATA
k2_nailuo-0.1.3.dist-info/RECORD
