Metadata-Version: 2.1
Name: k2-nailuo
Version: 0.1.3
Summary: FSA/FST algorithms, intended to (eventually) be interoperable with PyTorch and similar.
Home-page: https://github.com/open-speech/sequeender
License: MIT
Keywords: FSA,Speech,Machine earning
Author: Daniel Povey
Requires-Python: >=3.7,<4.0
Classifier: Development Status :: 2 - Pre-Alpha
Classifier: Intended Audience :: Developers
Classifier: Intended Audience :: Education
Classifier: Intended Audience :: Science/Research
Classifier: License :: OSI Approved :: MIT License
Classifier: Programming Language :: C++
Classifier: Programming Language :: Python :: 3
Classifier: Programming Language :: Python :: 3.7
Classifier: Programming Language :: Python :: 3.8
Classifier: Programming Language :: Python :: 3.9
Classifier: Topic :: Scientific/Engineering
Classifier: Topic :: Scientific/Engineering :: Artificial Intelligence
Classifier: Topic :: Scientific/Engineering :: Mathematics
Classifier: Topic :: Software Development
Classifier: Topic :: Software Development :: Libraries
Classifier: Topic :: Software Development :: Libraries :: Python Modules
Requires-Dist: graphviz (>=0.14.1,<0.15.0)
Requires-Dist: torch (>=1.6.0,<2.0.0)
Project-URL: Documentation, https://github.com/open-speech/sequeender
Project-URL: Repository, https://github.com/open-speech/sequeender
